{
  "employer": {
    "record_type": "H",
    "hq_number": "test1",
    "branch_number": "branch1",
    "year": "2022",
    "month": "5",
    "total_mtd": 1000.00,
    "total_mtd_record": 2,
    "total_cp38": 500.00,
    "total_cp38_record": 2
  },
  "employees": [
    {
      "record_type": "D",
      "tax_reference": "1001",
      "wife_code": "1",
      "name": "FOO BAR",
      "old_ic": "ABC12345",
      "new_ic": "ABC12345",
      "passport": "P123",
      "country_code": "99",
      "mtd_amount": 500,
      "cp38_amount": 250,
      "number": "9001"
    },
    {
      "record_type": "D",
      "tax_reference": "1002",
      "wife_code": "2",
      "name": "ALICE",
      "old_ic": "ABC999",
      "new_ic": "ABC999",
      "passport": "P999",
      "country_code": "99",
      "mtd_amount": 500,
      "cp38_amount": 250,
      "number": "9002"
    }
  ]
}